my_module/__init__.py
my_module/decorater_.py
my_module/rand_.py
izero_module-0.0.3.dist-info/METADATA
izero_module-0.0.3.dist-info/WHEEL
izero_module-0.0.3.dist-info/top_level.txt
izero_module-0.0.3.dist-info/RECORD
