Metadata-Version: 2.1
Name: izero-module
Version: 0.0.3
Summary: A simpler module, just for testing.
Author: zero
Author-email: 1546596867@qq.com
License: UNKNOWN
Platform: UNKNOWN
Requires-Python: >=3.6
